{
   "_id": "HDTjXQcZfChyAKTx",
   "effects": [],
   "flags": {},
   "folder": null,
   "img": "icons/magic/earth/lava-explosion-orange.webp",
   "name": "Earthquake",
   "ownership": {
      "default": 0,
      "eo6BalpqAg0Hf8ie": 3
   },
   "sort": 0,
   "system": {
      "complexity": 9,
      "description": "<div class=\"page\" title=\"Page 73\">\n<div class=\"layoutArea\">\n<div class=\"column\">\n<p>This spell can only be cast underground. It causes an earthquake in an area within short range of the target location. Any creature within that area takes +8 Health damage, which can be resisted with a Body roll.</p>\n</div>\n</div>\n</div>",
      "duration": "instant",
      "range": "short",
      "school": "Earth"
   },
   "type": "spell"
}
