{
   "_id": "yYSkTD8oSq6fMYjm",
   "effects": [],
   "flags": {},
   "folder": null,
   "img": "icons/magic/fire/projectile-meteor-salvo-heavy-red.webp",
   "name": "Meteor Swarm",
   "ownership": {
      "default": 0,
      "eo6BalpqAg0Hf8ie": 3
   },
   "sort": 0,
   "system": {
      "complexity": 12,
      "description": "<div class=\"page\" title=\"Page 75\">\n<div class=\"layoutArea\">\n<div class=\"column\">\n<p>This spell can only be cast under the open sky. A swarm of balls of fire appear from the sky, landing in such a way as to fill the area within short range of the target location. The fire will do +6 Health damage to any creatures in the affected area, which may be resisted by a Body roll.</p>\n</div>\n</div>\n</div>",
      "duration": "instant",
      "range": "sight",
      "school": "Fire"
   },
   "type": "spell"
}
